{
  "generated": "2026-06-15 02:14",
  "results": {
    "MEX-RSA": {
      "home": 2,
      "away": 0
    },
    "KOR-CZE": {
      "home": 2,
      "away": 1
    },
    "CAN-BIH": {
      "home": null,
      "away": null
    },
    "USA-PAR": {
      "home": 4,
      "away": 1
    },
    "QAT-SUI": {
      "home": 1,
      "away": 1
    },
    "BRA-MAR": {
      "home": 1,
      "away": 1
    },
    "HAI-SCO": {
      "home": 0,
      "away": 1
    },
    "AUS-TUR": {
      "home": 2,
      "away": 0
    },
    "GER-CUW": {
      "home": 7,
      "away": 1
    },
    "NED-JPN": {
      "home": 2,
      "away": 2
    },
    "CIV-ECU": {
      "home": 1,
      "away": 0
    }
  }
}